setup.py
FlightReportManager/DataStoreController.py
FlightReportManager/FileStorageController.py
FlightReportManager/FlightReportManager.py
FlightReportManager/PlotGPSTrack.py
FlightReportManager/Plotlib.py
FlightReportManager/RunFlightReportManager
FlightReportManager/__init__.py
FlightReportManager.egg-info/PKG-INFO
FlightReportManager.egg-info/SOURCES.txt
FlightReportManager.egg-info/dependency_links.txt
FlightReportManager.egg-info/requires.txt
FlightReportManager.egg-info/top_level.txt