Metadata-Version: 1.0
Name: FlightReportManager
Version: 0.3
Summary: Store and manage your Parrot Bebop flights. Visualise your flight and export it to many different formats.
Home-page: https://johanneskinzig.de/software-development/flightreportmanager.html
Author: Johannes Kinzig
Author-email: johannes_kinzig@icloud.com
License: Apache License, Version 2.0
Platform: UNKNOWN
